awx_plugins/interfaces/_temporary_private_api.py
awx_plugins/interfaces/_temporary_private_container_api.py
awx_plugins/interfaces/_temporary_private_credential_api.py
awx_plugins/interfaces/_temporary_private_django_api.py
awx_plugins/interfaces/_temporary_private_inject_api.py
awx_plugins/interfaces/_temporary_private_licensing_api.py
awx_plugins/interfaces/api.py
awx_plugins/interfaces/py.typed
awx_plugins.interfaces-0.0.1a5.dist-info/LICENSE
awx_plugins.interfaces-0.0.1a5.dist-info/METADATA
awx_plugins.interfaces-0.0.1a5.dist-info/WHEEL
awx_plugins.interfaces-0.0.1a5.dist-info/top_level.txt
awx_plugins.interfaces-0.0.1a5.dist-info/RECORD
