Metadata-Version: 2.1
Name: awx_plugins.interfaces
Version: 0.0.1a5
Summary: Common interfaces for implementing plugins to AWX.
Author: Ansible maintainers and contributors
License: 
Project-URL: Homepage, https://docs.ansible.com
Project-URL: Chat: Discuss Forum, https://forum.ansible.com
Project-URL: Chat: Matrix, https://matrix.to/#/#awx:ansible.com
Project-URL: CI: GitHub, https://github.com/ansible/awx_plugins.interfaces/actions/workflows/ci-cd.yml
Project-URL: Docs: RTD, https://awx-plugins-interfaces.rtfd.io
Project-URL: GitHub: issues, https://github.com/ansible/awx_plugins.interfaces/issues
Project-URL: GitHub: repo, https://github.com/ansible/awx_plugins.interfaces
Keywords: Ansible,AWX
Classifier: Development Status :: 1 - Planning
Classifier: Environment :: Web Environment
Classifier: Framework :: Ansible
Classifier: Intended Audience :: System Administrators
Classifier: License :: OSI Approved :: Apache Software License
Classifier: Operating System :: POSIX :: Linux
Classifier: Programming Language :: Python :: 3
Classifier: Programming Language :: Python :: 3.11
Classifier: Programming Language :: Python :: 3.12
Classifier: Programming Language :: Python :: 3.13
Classifier: Topic :: System :: Systems Administration
Classifier: Typing :: Typed
Requires-Python: >=3.11
License-File: LICENSE
